archiTop/__init__.py
archiTop/__main__.py
archiTop/config.ini
archiTop/config.py
archiTop/data_types.py
archiTop/base_classes/__init__.py
archiTop/base_classes/deck_builder.py
archiTop/base_classes/deck_fetcher.py
archiTop/deck_builder/__init__.py
archiTop/deck_builder/final_deck_builder.py
archiTop/deck_builder/multi_card_deck_builder.py
archiTop/deck_builder/single_card_deck_builder.py
archiTop/deck_fetcher/__init__.py
archiTop/deck_fetcher/archidekt.py
archiTop/deck_fetcher/moxfield.py
archiTop/resources/__init__.py
archiTop/resources/templates.py
archiTop/scryfall/__init__.py
archiTop/scryfall/data_types.py
archiTop/scryfall/scryfall_builder.py
archiTop/scryfall/scryfall_fetcher.py
archiTop/scryfall/scryfall_loader.py
tests/__init__.py
ArchiTop-0.3.1.dist-info/LICENSE
ArchiTop-0.3.1.dist-info/METADATA
ArchiTop-0.3.1.dist-info/WHEEL
ArchiTop-0.3.1.dist-info/entry_points.txt
ArchiTop-0.3.1.dist-info/top_level.txt
ArchiTop-0.3.1.dist-info/RECORD
