Metadata-Version: 2.1
Name: ArchiTop
Version: 0.3.1
Summary: Archidekt to TableTop export cli
Home-page: https://github.com/Julian-Brendel/archiTop
Author: Julian Brendel
Author-email: julian.brendel@t-online.de
License: LICENSE
Platform: UNKNOWN
Requires-Python: >=3.8
Requires-Dist: requests (>=2.24)
Requires-Dist: logging-spinner (>=0.2.2)
